{"version":1,"resource":"file:///Users/whlin/Library/CloudStorage/OneDrive-HKUSTConnect/Documents/python/my_notes_py/ad-hoc%20code/file_management/file_manage.ipynb","entries":[{"id":"ZHzC.ipynb","source":"edit","timestamp":1653207819859},{"id":"ryQn.ipynb","source":"edit","timestamp":1653207833276},{"id":"FDOl.ipynb","source":"edit","timestamp":1653207843966},{"id":"oqPQ.ipynb","source":"edit","timestamp":1653207883349},{"id":"aRTU.ipynb","source":"edit","timestamp":1653207907512},{"id":"0QQz.ipynb","source":"Insert Cell","timestamp":1653207935601},{"id":"eMZB.ipynb","source":"Insert Cell","timestamp":1653207979137},{"id":"f6yE.ipynb","source":"Insert Cell","timestamp":1653208042410},{"id":"mmGJ.ipynb","source":"Insert Cell","timestamp":1653208137596},{"id":"qYDh.ipynb","source":"Insert Cell","timestamp":1653208202282},{"id":"y9Hr.ipynb","source":"edit","timestamp":1653208211549},{"id":"UwDV.ipynb","source":"edit","timestamp":1653209139046},{"id":"8Kr3.ipynb","source":"edit","timestamp":1653209191220},{"id":"zSJF.ipynb","source":"edit","timestamp":1653209222926},{"id":"tQPc.ipynb","source":"edit","timestamp":1653209233135},{"id":"WtvL.ipynb","source":"edit","timestamp":1653209255072},{"id":"oPYj.ipynb","source":"edit","timestamp":1653209370076},{"id":"GN9d.ipynb","source":"edit","timestamp":1653209426958},{"id":"J9ob.ipynb","source":"edit","timestamp":1653209440732},{"id":"3SVr.ipynb","source":"edit","timestamp":1653209481218},{"id":"0OYH.ipynb","source":"edit","timestamp":1653209509416},{"id":"fvF5.ipynb","source":"edit","timestamp":1653209528504},{"id":"CZmR.ipynb","source":"edit","timestamp":1653209570450},{"id":"vCkU.ipynb","source":"edit","timestamp":1653209591692},{"id":"C6bZ.ipynb","source":"edit","timestamp":1653209620643},{"id":"SXFd.ipynb","timestamp":1653209740161},{"id":"e8S8.ipynb","source":"edit","timestamp":1653209783840},{"id":"wmhl.ipynb","source":"edit","timestamp":1653209847758},{"id":"uz7m.ipynb","source":"edit","timestamp":1653209862149},{"id":"STKD.ipynb","source":"edit","timestamp":1653209877626},{"id":"2t1a.ipynb","source":"edit","timestamp":1653209896283},{"id":"uMQf.ipynb","source":"edit","timestamp":1653209925281},{"id":"yZLD.ipynb","source":"edit","timestamp":1653210046115},{"id":"Eubb.ipynb","source":"Insert Cell","timestamp":1653210081034},{"id":"eFnJ.ipynb","source":"edit","timestamp":1653210126965},{"id":"Mekw.ipynb","source":"edit","timestamp":1653210149773},{"id":"LmSE.ipynb","source":"edit","timestamp":1653210171686},{"id":"H6vz.ipynb","source":"Insert Cell","timestamp":1653210449589},{"id":"UNWs.ipynb","source":"Insert Cell","timestamp":1653210516190},{"id":"VhNh.ipynb","timestamp":1653308335512},{"id":"UolV.ipynb","source":"undoRedo.source","timestamp":1653784634394},{"id":"VC5g.ipynb","source":"edit","timestamp":1653784654104},{"id":"RdcV.ipynb","source":"undoRedo.source","timestamp":1653784664139},{"id":"3p1A.ipynb","source":"edit","timestamp":1653784709778},{"id":"GZE6.ipynb","source":"edit","timestamp":1653784749484},{"id":"U9WB.ipynb","source":"edit","timestamp":1653784785623},{"id":"9DkI.ipynb","source":"edit","timestamp":1653784849859},{"id":"oX7J.ipynb","source":"edit","timestamp":1653784878647},{"id":"jk2w.ipynb","source":"edit","timestamp":1653792866757},{"id":"1XE2.ipynb","timestamp":1654418842479}]}